TuijianXitongZhiSuanfaLibrecZhongwenWendang/README.md
TuijianXitongZhiSuanfaLibrecZhongwenWendang/__init__.py
TuijianXitongZhiSuanfaLibrecZhongwenWendang/__main__.py
TuijianXitongZhiSuanfaLibrecZhongwenWendang/file.epub
TuijianXitongZhiSuanfaLibrecZhongwenWendang/index.html
TuijianXitongZhiSuanfaLibrecZhongwenWendang/css/__init__.py
TuijianXitongZhiSuanfaLibrecZhongwenWendang/css/annotations.css
TuijianXitongZhiSuanfaLibrecZhongwenWendang/css/main.css
TuijianXitongZhiSuanfaLibrecZhongwenWendang/css/normalize.css
TuijianXitongZhiSuanfaLibrecZhongwenWendang/css/popup.css
TuijianXitongZhiSuanfaLibrecZhongwenWendang/font/__init__.py
TuijianXitongZhiSuanfaLibrecZhongwenWendang/font/fontello.eot
TuijianXitongZhiSuanfaLibrecZhongwenWendang/font/fontello.svg
TuijianXitongZhiSuanfaLibrecZhongwenWendang/font/fontello.ttf
TuijianXitongZhiSuanfaLibrecZhongwenWendang/font/fontello.woff
TuijianXitongZhiSuanfaLibrecZhongwenWendang/img/__init__.py
TuijianXitongZhiSuanfaLibrecZhongwenWendang/img/annotator-glyph-sprite.png
TuijianXitongZhiSuanfaLibrecZhongwenWendang/img/annotator-icon-sprite.png
TuijianXitongZhiSuanfaLibrecZhongwenWendang/img/apple-touch-icon.png
TuijianXitongZhiSuanfaLibrecZhongwenWendang/img/cancelfullscreen.png
TuijianXitongZhiSuanfaLibrecZhongwenWendang/img/close.png
TuijianXitongZhiSuanfaLibrecZhongwenWendang/img/fullscreen.png
TuijianXitongZhiSuanfaLibrecZhongwenWendang/img/loader.gif
TuijianXitongZhiSuanfaLibrecZhongwenWendang/img/menu-icon.png
TuijianXitongZhiSuanfaLibrecZhongwenWendang/img/save.png
TuijianXitongZhiSuanfaLibrecZhongwenWendang/img/saved.png
TuijianXitongZhiSuanfaLibrecZhongwenWendang/img/settings-s.png
TuijianXitongZhiSuanfaLibrecZhongwenWendang/img/settings.png
TuijianXitongZhiSuanfaLibrecZhongwenWendang/img/star.png
TuijianXitongZhiSuanfaLibrecZhongwenWendang/js/__init__.py
TuijianXitongZhiSuanfaLibrecZhongwenWendang/js/epub.js
TuijianXitongZhiSuanfaLibrecZhongwenWendang/js/epub.min.js
tuijian_xitong_zhi_suanfa_librec_zhongwen_wendang-2024.3.3.0.dist-info/METADATA
tuijian_xitong_zhi_suanfa_librec_zhongwen_wendang-2024.3.3.0.dist-info/WHEEL
tuijian_xitong_zhi_suanfa_librec_zhongwen_wendang-2024.3.3.0.dist-info/entry_points.txt
tuijian_xitong_zhi_suanfa_librec_zhongwen_wendang-2024.3.3.0.dist-info/top_level.txt
tuijian_xitong_zhi_suanfa_librec_zhongwen_wendang-2024.3.3.0.dist-info/RECORD
